<?xml version="1.0" encoding="utf-8"?>
<AnalysisInput xmlns:xsi="http://www.w3.org/2001/XMLSchema-instance" xmlns:xsd="http://www.w3.org/2001/XMLSchema">
    <Settings>
        <Setting>
            <Key>sonar.cs.analyzeGeneratedCode</Key>
            <Value>false</Value>
        </Setting>
    </Settings>
    <Rules>
        <Rule>
            <Key>S1451</Key>
            <Parameters>
                <Parameter>
                    <Key>headerFormat</Key>
                    <Value>// Copyright © R1RCM. All Rights Reserved.</Value>
                </Parameter>
                <Parameter>
                    <Key>isRegularExpression</Key>
                    <Value>false</Value>
                </Parameter>
            </Parameters>
        </Rule>
    </Rules>
</AnalysisInput>